Metadata-Version: 2.1
Name: http-query
Version: 0.0.2
Summary: Dont install this package, purely testing purpose
Author: Tilak Thimmappa
